<annotation>
	<folder>NoMask_Annotated_Images</folder>
	<filename>1988.jpg</filename>
	<path>D:\ML-Projects\DATA 1\NoMask_Annotated_Images\1988.jpg</path>
	<source>
		<database>Unknown</database>
	</source>
	<size>
		<width>2000</width>
		<height>1333</height>
		<depth>3</depth>
	</size>
	<segmented>0</segmented>
	<object>
		<name>without_mask</name>
		<pose>Unspecified</pose>
		<truncated>0</truncated>
		<difficult>0</difficult>
		<bndbox>
			<xmin>455</xmin>
			<ymin>212</ymin>
			<xmax>706</xmax>
			<ymax>491</ymax>
		</bndbox>
	</object>
</annotation>
