<annotation>
	<folder>NoMask_Annotated_Images</folder>
	<filename>4784.png</filename>
	<path>D:\ML-Projects\DATA 1\NoMask_Annotated_Images\4784.png</path>
	<source>
		<database>Unknown</database>
	</source>
	<size>
		<width>699</width>
		<height>593</height>
		<depth>3</depth>
	</size>
	<segmented>0</segmented>
	<object>
		<name>without_mask</name>
		<pose>Unspecified</pose>
		<truncated>0</truncated>
		<difficult>0</difficult>
		<bndbox>
			<xmin>386</xmin>
			<ymin>78</ymin>
			<xmax>479</xmax>
			<ymax>202</ymax>
		</bndbox>
	</object>
</annotation>
