<annotation>
	<folder>NoMask_Annotated_Images</folder>
	<filename>4793.png</filename>
	<path>D:\ML-Projects\DATA 1\NoMask_Annotated_Images\4793.png</path>
	<source>
		<database>Unknown</database>
	</source>
	<size>
		<width>453</width>
		<height>583</height>
		<depth>1</depth>
	</size>
	<segmented>0</segmented>
	<object>
		<name>without_mask</name>
		<pose>Unspecified</pose>
		<truncated>0</truncated>
		<difficult>0</difficult>
		<bndbox>
			<xmin>95</xmin>
			<ymin>52</ymin>
			<xmax>324</xmax>
			<ymax>317</ymax>
		</bndbox>
	</object>
</annotation>
